{"version":1,"resource":"file:///home/lullaby/Projects/Safepill/safepill-frontend/components/Footer.vue","entries":[{"id":"FgzJ.vue","timestamp":1694098780075},{"id":"pEOX.vue","source":"renamed.source","timestamp":1694099478430},{"id":"Fbh9.vue","timestamp":1694100187199},{"id":"yXLF.vue","timestamp":1694289018644},{"id":"cdWO.vue","timestamp":1694289131954},{"id":"1OSg.vue","source":"undoRedo.source","timestamp":1694289145401},{"id":"L8cq.vue","timestamp":1694308112618},{"id":"4YMU.vue","timestamp":1694308245971},{"id":"4WMR.vue","timestamp":1694308271581},{"id":"RaR2.vue","timestamp":1694308320144},{"id":"bv2k.vue","timestamp":1694308337688},{"id":"OXDW.vue","timestamp":1694308602214},{"id":"xKoh.vue","timestamp":1694308691708},{"id":"lvjE.vue","timestamp":1694308724658},{"id":"D6HF.vue","timestamp":1694308796961},{"id":"GHd4.vue","timestamp":1694308858908},{"id":"rGkG.vue","timestamp":1694308892084},{"id":"hiy1.vue","timestamp":1694308940748},{"id":"aO3m.vue","timestamp":1694308958011},{"id":"ojRC.vue","source":"searchReplace.source","timestamp":1694390785978}]}